[
  {
    "title": "Testing",
    "type": "victory",
    "description": "win",
    "timestamp": "2025-07-04T15:39:17.342224"
  },
  {
    "title": "Title",
    "type": "victory",
    "description": "",
    "timestamp": "2025-07-03T19:23:00.021026"
  },
  {
    "title": "Title",
    "type": "victory",
    "description": "",
    "timestamp": "2025-07-03T19:19:35.342952"
  },
  {
    "title": "Title",
    "type": "victory",
    "description": "",
    "timestamp": "2025-07-03T19:17:04.931063"
  },
  {
    "title": "Title",
    "type": "victory",
    "description": "",
    "timestamp": "2025-07-03T19:16:48.898004"
  },
  {
    "title": "Title",
    "type": "victory",
    "description": "",
    "timestamp": "2025-07-03T19:16:10.489220"
  },
  {
    "title": "Title",
    "type": "victory",
    "description": "",
    "timestamp": "2025-07-03T19:15:28.599675"
  },
  {
    "title": "no",
    "type": "setback",
    "description": "yes",
    "timestamp": "2025-07-03T19:15:00.991146"
  },
  {
    "title": "Title",
    "type": "victory",
    "description": "",
    "timestamp": "2025-07-03T19:12:47.123236"
  },
  {
    "title": "2025.07.03",
    "type": "victory",
    "description": "I did'nt give in to temptation\n\nwatched a sermon and all\n\nbeen ab 5 days free from porn thanks Jesus, sadly not from fornication that is a hard thing to break, its not even for a reason, just kinda a habit but thats okay , i mean for now I'm going one day at a time",
    "timestamp": "2025-07-03T18:56:14.118268"
  }
]